llmconnect/__init__.py
llmconnect/base.py
llmconnect/llmconnect.py
llmconnect/providers/__init__.py
llmconnect/providers/claude_llm.py
llmconnect/providers/deepseek_llm.py
llmconnect/providers/gemini_llm.py
llmconnect/providers/llama_llm.py
llmconnect/providers/mistral_llm.py
llmconnect/providers/openai_llm.py
llmconnect/providers/perplexity_llm.py
tests/__init__.py
tests/test_llmconnect.py
tests/test_providers.py
llm_api_bridge-1.0.0.dist-info/METADATA
llm_api_bridge-1.0.0.dist-info/WHEEL
llm_api_bridge-1.0.0.dist-info/top_level.txt
llm_api_bridge-1.0.0.dist-info/RECORD
