Metadata-Version: 2.4
Name: llm-api-bridge
Version: 1.0.0
Summary: A unified interface for querying multiple LLM providers via REST APIs
Home-page: https://github.com/Hunzala-Rasheed1/llmconnect
Author: Hunzala Rasheed
Author-email: hunzalarasheed14@gmail.com
Project-URL: Bug Reports, https://github.com/Hunzala-Rasheed1/llmconnect/issues
Project-URL: Source, https://github.com/yourusername/llmconnect
Project-URL: Documentation, https://github.com/Hunzala-Rasheed1/llmconnect#readme
Keywords: llm,ai,openai,claude,gemini,api,chatbot,nlp
Classifier: Development Status :: 4 - Beta
Classifier: Intended Audience :: Developers
Classifier: License :: OSI Approved :: MIT License
Classifier: Operating System :: OS Independent
Classifier: Programming Language :: Python :: 3
Classifier: Programming Language :: Python :: 3.7
Classifier: Programming Language :: Python :: 3.8
Classifier: Programming Language :: Python :: 3.9
Classifier: Programming Language :: Python :: 3.10
Classifier: Programming Language :: Python :: 3.11
Classifier: Programming Language :: Python :: 3.12
Classifier: Topic :: Software Development :: Libraries :: Python Modules
Classifier: Topic :: Internet :: WWW/HTTP :: Dynamic Content
Classifier: Topic :: Scientific/Engineering :: Artificial Intelligence
Requires-Python: >=3.7
Requires-Dist: requests>=2.25.0
Provides-Extra: dev
Requires-Dist: pytest>=6.0; extra == "dev"
Requires-Dist: black>=21.0; extra == "dev"
Requires-Dist: flake8>=3.8; extra == "dev"
Requires-Dist: python-dotenv>=0.19.0; extra == "dev"
Dynamic: author
Dynamic: author-email
Dynamic: classifier
Dynamic: description
Dynamic: description-content-type
Dynamic: home-page
Dynamic: keywords
Dynamic: project-url
Dynamic: provides-extra
Dynamic: requires-dist
Dynamic: requires-python
Dynamic: summary
